dukhi/__init__.py
dukhi/api.py
dukhi/middleware.py
dukhi/response.py
dukhi-0.0.1.dist-info/METADATA
dukhi-0.0.1.dist-info/WHEEL
dukhi-0.0.1.dist-info/top_level.txt
dukhi-0.0.1.dist-info/RECORD
