Metadata-Version: 2.1
Name: dukhi
Version: 0.0.1
Summary: Dukhi Bumbo Python Web Framework built for learning purposes.
Author: SMANES
Author-email: manes.saraj@gmail.com
License: MIT
Platform: UNKNOWN
Classifier: Programming Language :: Python :: 3.6
Requires-Python: >=3.6.0
Requires-Dist: Jinja2 (==3.1.1)
Requires-Dist: parse (==1.19.0)
Requires-Dist: requests (==2.22.0)
Requires-Dist: requests-wsgi-adapter (==0.4.1)
Requires-Dist: WebOb (==1.8.7)
Requires-Dist: whitenoise (==6.0.0)
